linkcheckmd/__init__.py
linkcheckmd/__main__.py
linkcheckmd/base.py
linkcheckmd/coro.py
linkcheckmd/files.py
linkcheckmd/sync.py
linkcheckmd/tests/__init__.py
linkcheckmd/tests/badlink.md
linkcheckmd/tests/test_script.py
mkdocs_linkcheck/__init__.py
mkdocs_linkcheck/__main__.py
mkdocs_linkcheck/base.py
mkdocs_linkcheck/coro.py
mkdocs_linkcheck/files.py
mkdocs_linkcheck/sync.py
mkdocs_linkcheck/tests/__init__.py
mkdocs_linkcheck/tests/badlink.md
mkdocs_linkcheck/tests/test_script.py
mkdocs_linkcheck-1.0.6.dist-info/LICENSE.txt
mkdocs_linkcheck-1.0.6.dist-info/METADATA
mkdocs_linkcheck-1.0.6.dist-info/WHEEL
mkdocs_linkcheck-1.0.6.dist-info/entry_points.txt
mkdocs_linkcheck-1.0.6.dist-info/top_level.txt
mkdocs_linkcheck-1.0.6.dist-info/RECORD
