Metadata-Version: 2.1
Name: mkdocs_linkcheck
Version: 1.0.6
Summary: Check links for Mkdocs-based sites, as well as any markdown-based website
Home-page: https://github.com/byrnereese/mkdocs-linkchecker
Author: Byrne Reese
Author-email: byrne@majordojo.com
License: UNKNOWN
Keywords: markdown,mkdocs,jekyll,hugo
Platform: UNKNOWN
Classifier: Development Status :: 5 - Production/Stable
Classifier: Environment :: Console
Classifier: Framework :: AsyncIO
Classifier: Intended Audience :: Developers
Classifier: Operating System :: OS Independent
Classifier: Programming Language :: Python :: 3
Classifier: Programming Language :: Python :: Implementation :: CPython
Classifier: Topic :: Internet :: WWW/HTTP :: Site Management :: Link Checking
Requires-Python: >=3.7
Provides-Extra: tests
Provides-Extra: lint
Provides-Extra: requests
